{
  "call_id": "S0000001",
  "source_file": "刘彩霞2打给王科 2025-10-28 15_12_27.",
  "total_duration_sec": 918.288,
  "annotated_turns": 35,
  "annotation_note": "管理员人工精标，用于 Gold Set 考题和标注质量参考",
  "turns": [
    {
      "turn_id": 1,
      "speaker": "sales",
      "start": 2.96,
      "end": 14.74,
      "duration_sec": 11.78,
      "input": {
        "text_asr": "喂，哎你好，王总，嗯，我是上午跟你啊，我是上午给你打电话的，做记账报税的那个。对啊。嗯这会儿有时间，不咱抽出几分钟的时间了解一下我们这个小程序，好吧？",
        "wav_path": "data/S0000001/A0000001.wav",
        "auto_emotion_hint": "中立"
      },
      "output": {
        "transcript_corrected": "喂，哎你好，王总，嗯，我是上午跟你啊，我是上午给你打电话的，做记账报税的那个。诶。嗯这会儿有时间，不咱抽出几分钟的时间了解一下我们这个小程序，好吧？",
        "emotion": "中立",
        "sales_strategy": "开场白/自我介绍",
        "customer_intent": "N/A-销售turn",
        "paralinguistic": [
          "无"
        ],
        "notes": "用户在对话中回答了一个嗯，和一个诶。属于正常反馈。不过识别中没进行区分"
      }
    },
    {
      "turn_id": 2,
      "speaker": "sales",
      "start": 14.74,
      "end": 22.24,
      "duration_sec": 7.5,
      "input": {
        "text_asr": "好喂，王总哦，可以可以。",
        "wav_path": "data/S0000001/A0000002.wav",
        "auto_emotion_hint": "中立"
      },
      "output": {
        "transcript_corrected": "好哇。喂，王总？ 哦，可以可以。",
        "emotion": "中立",
        "sales_strategy": "关系维护/寒暄",
        "customer_intent": "N/A-销售turn",
        "paralinguistic": [
          "无"
        ],
        "notes": "此turn实际包含客户回应\"哦/可以可以\"，diarization未分离出来。中间有约2秒沉默。\n客户回应\"可以可以\"，意图=有兴趣/积极回应"
      }
    },
    {
      "turn_id": 3,
      "speaker": "sales",
      "start": 22.52,
      "end": 33.575,
      "duration_sec": 11.055,
      "input": {
        "text_asr": "嗯，好行，嗯，上午有给您发一个小程序，嗯，干嘛账？用手机轻松记账报税这个小程序，你把它打开，然后我带你体验一下小程序的一个操作流程。",
        "wav_path": "data/S0000001/A0000003.wav",
        "auto_emotion_hint": "中立"
      },
      "output": {
        "transcript_corrected": "嗯，好行，嗯，上午有给您发一个小程序，嗯，伽马账？用手机轻松记账报税这个小程序，你把它打开，然后我带你体验一下小程序的一个操作流程。",
        "emotion": "中立",
        "sales_strategy": "产品介绍",
        "customer_intent": "N/A-销售turn",
        "paralinguistic": [
          "无"
        ],
        "notes": "这一段识别正确，伽马账这个专有词，已修复。"
      }
    },
    {
      "turn_id": 4,
      "speaker": "sales",
      "start": 38.64,
      "end": 43.055,
      "duration_sec": 4.415,
      "input": {
        "text_asr": "就是咱俩微信聊天的界面，有一个有一个我给你发的有一个小程序。",
        "wav_path": "data/S0000001/A0000004.wav",
        "auto_emotion_hint": "中立"
      },
      "output": {
        "transcript_corrected": "就是咱俩微信聊天的界面，有一个有一个我给你发的有一个小程序。",
        "emotion": "中立",
        "sales_strategy": "产品介绍",
        "customer_intent": "N/A-销售turn",
        "paralinguistic": [
          "无"
        ],
        "notes": null
      }
    },
    {
      "turn_id": 5,
      "speaker": "sales",
      "start": 46.08,
      "end": 56.19,
      "duration_sec": 10.11,
      "input": {
        "text_asr": "嗯啊然后嗯，小程序的话，你打开右上角有一个注册登录，它就跟美团啊、滴滴打车一样的，小程序需要您接受一个验证。",
        "wav_path": "data/S0000001/A0000005.wav",
        "auto_emotion_hint": "中立"
      },
      "output": {
        "transcript_corrected": "嗯~~~ 嗯，小程序的话，你打开右上角有一个注册登录，它就跟美团啊、滴滴打车一样的，小程序需要您接受一个验证。",
        "emotion": "中立",
        "sales_strategy": "产品介绍",
        "customer_intent": "N/A-销售turn",
        "paralinguistic": [
          "无"
        ],
        "notes": "开始的嗯是用户拖音，估计是在一边跟着操作，一边研究\n用户在最后在销售说话时重复里几个音节，试图打断销售。"
      }
    },
    {
      "turn_id": 6,
      "speaker": "customer",
      "start": 56.19,
      "end": 56.85,
      "duration_sec": 0.66,
      "input": {
        "text_asr": "微信名叫啥？",
        "wav_path": "data/S0000001/B0000001.wav",
        "auto_emotion_hint": "中立"
      },
      "output": {
        "transcript_corrected": "你的微信名叫啥？",
        "emotion": "中立",
        "sales_strategy": "N/A-客户turn",
        "customer_intent": "提问/深入了解",
        "paralinguistic": [
          "无"
        ],
        "notes": "前部分分离了部分销售上一句完整句子少的两个字。后面就是纯用户提问了"
      }
    },
    {
      "turn_id": 7,
      "speaker": "customer",
      "start": 56.85,
      "end": 58.03,
      "duration_sec": 1.18,
      "input": {
        "text_asr": "你微信名叫啥？",
        "wav_path": "data/S0000001/B0000002.wav",
        "auto_emotion_hint": "中立"
      },
      "output": {
        "transcript_corrected": "你微信名叫啥？",
        "emotion": "中立",
        "sales_strategy": "N/A-客户turn",
        "customer_intent": "提问/深入了解",
        "paralinguistic": [
          "无"
        ],
        "notes": "属于上一句跟着的重复，其实可以合并在一起"
      }
    },
    {
      "turn_id": 8,
      "speaker": "sales",
      "start": 58.03,
      "end": 63.825,
      "duration_sec": 5.795,
      "input": {
        "text_asr": "嗯，刚刚马上才对客服留在家，我现在再给您发一个握龊的表情，你看一下。",
        "wav_path": "data/S0000001/A0000006.wav",
        "auto_emotion_hint": "中立"
      },
      "output": {
        "transcript_corrected": "嗯，伽马账财税客服刘彩霞，我现在再给您发一个握手的表情，你看一下。",
        "emotion": "中立",
        "sales_strategy": "关系维护/寒暄",
        "customer_intent": "N/A-销售turn",
        "paralinguistic": [
          "无"
        ],
        "notes": null
      }
    },
    {
      "turn_id": 9,
      "speaker": "unknown",
      "start": 65.93,
      "end": 67.91,
      "duration_sec": 1.98,
      "input": {
        "text_asr": "嗯，啊晚安。",
        "wav_path": "data/S0000001/U0000001.wav",
        "auto_emotion_hint": "中立"
      },
      "output": {
        "transcript_corrected": "/",
        "emotion": "中立",
        "sales_strategy": "N/A-客户turn",
        "customer_intent": "N/A-销售turn",
        "paralinguistic": [
          "无"
        ],
        "notes": "这段是空的"
      }
    },
    {
      "turn_id": 10,
      "speaker": "sales",
      "start": 71.6,
      "end": 78.78,
      "duration_sec": 7.18,
      "input": {
        "text_asr": "好的，这个啊啊对我上午有给您发，又给你发了个的表情。",
        "wav_path": "data/S0000001/A0000007.wav",
        "auto_emotion_hint": "中立"
      },
      "output": {
        "transcript_corrected": "好的，这个啊啊。对我上午有给您发，又给你发了个握手的表情。",
        "emotion": "中立",
        "sales_strategy": null,
        "customer_intent": "中性/观望",
        "paralinguistic": [
          "无"
        ],
        "notes": "开始是客户提问，然后又是销售回答，没有分割开"
      }
    },
    {
      "turn_id": 11,
      "speaker": "sales",
      "start": 78.78,
      "end": 84.8,
      "duration_sec": 6.02,
      "input": {
        "text_asr": "嗯，我我打开的小程序，然后呢，小程序右上角有一个注册登录。",
        "wav_path": "data/S0000001/A0000008.wav",
        "auto_emotion_hint": "中立"
      },
      "output": {
        "transcript_corrected": "嗯，我我打开的小程序，然后呢？小程序右上角有一个注册登录。",
        "emotion": "中立",
        "sales_strategy": "N/A-客户turn",
        "customer_intent": "提问/深入了解",
        "paralinguistic": [
          "无"
        ],
        "notes": "这也是一段对话没有分割，前面是客户提问到然后呢？后面是销售解释。"
      }
    },
    {
      "turn_id": 12,
      "speaker": "sales",
      "start": 84.8,
      "end": 113.22,
      "duration_sec": 28.42,
      "input": {
        "text_asr": "嗯，啊注册登录的话，您只需要用咱们那个五五八八的手机号接收一个验证码，然后嗯就是就注册了病入所中去。嗯，对，登录手机快的号啊嗯手机号快捷登录。我明白啊，登录好以后，还是在右上角有一个嗯创建公司。",
        "wav_path": "data/S0000001/A0000009.wav",
        "auto_emotion_hint": "中立"
      },
      "output": {
        "transcript_corrected": "嗯，啊注册登录的话，您只需要用咱们那个五五八八的手机号接收一个验证码，然后嗯就是就注册了。应用小程序。嗯，对，登录手机快捷号。啊嗯手机号快捷登录。登录好以后，还是在右上角，有一个嗯创建公司。",
        "emotion": "中立",
        "sales_strategy": "关系维护/寒暄",
        "customer_intent": "N/A-销售turn",
        "paralinguistic": [
          "无"
        ],
        "notes": "中间依旧包含了对话，没有分割。没分割部分之前，有明显无对话，比如应用小程序。还有对，登录手机快捷号。这个是客户回的。创建公司两边都一起重复了。"
      }
    },
    {
      "turn_id": 13,
      "speaker": "customer",
      "start": 113.22,
      "end": 120.81,
      "duration_sec": 7.59,
      "input": {
        "text_asr": "你看到没？",
        "wav_path": "data/S0000001/B0000003.wav",
        "auto_emotion_hint": "中立"
      },
      "output": {
        "transcript_corrected": "嗯。",
        "emotion": "中立",
        "sales_strategy": "N/A-客户turn",
        "customer_intent": "中性/观望",
        "paralinguistic": [
          "无"
        ],
        "notes": null
      }
    },
    {
      "turn_id": 14,
      "speaker": "sales",
      "start": 120.81,
      "end": 210.52,
      "duration_sec": 89.71,
      "input": {
        "text_asr": "嗯嗯，创建公司嗯，对你跟我说啊，创建成功以后，回到咱们的一个账后，搞定记账。看到没？嗯，呃，商户搞定记账。第一步的话是哦，您这家公司是一般纳税人公司是吧？哦，就是开专校的嗯嗯，然后三步搞定提成，第一步就是员工与工资。那首先呢咱们需要把呃第一次需要把咱们公司有几个员工在职做申报，把这个信息给添加上去。如果说后期员工没有变更的情况下，我们申报呃，申报的话，就以咱第一次添加了为准。如果说后期嗯咱员工有入职，离职上面可以做改变。你先选点击选择员工，先添加一个信息。后续的话有其他员工呃再往上面加，也可以在右上角有一个选择员工，然后有一个加号键，你就把员工的信息给啊员工的信息、姓名、啊、证件号这些你给输入上去。然后入职时间呢，我们就填过营业执照以后的时间就可以了。印发工资呢，建议五千以下嗯，这个员工如果说没有在这你这家公司缴纳社保的话，这个缴纳社保的按钮你就不用管了。那如果说他有缴纳社保的话，你就把这个按钮给打开。",
        "wav_path": "data/S0000001/A0000010.wav",
        "auto_emotion_hint": "中立"
      },
      "output": {
        "transcript_corrected": "嗯嗯，创建公司嗯，对你跟我说啊，创建成功以后，回到咱们的一个三步搞定记账。看到没？嗯，呃，三步搞定记账。第一步的话是哦，您这家公司是一般纳税人公司是吧？哦，就是开专校的。嗯嗯，然后三步搞定记账，第一步就是员工与工资。那首先呢咱们需要把呃第一次需要把咱们公司有几个员工在职做申报，把这个信息给添加上去。如果说后期员工没有变更的情况下，我们申报呃，申报的话，就以咱第一次添加了为准。如果说后期嗯咱员工有入职，离职上面可以做改变。你先选点击选择员工，先添加一个信息。后续的话有其他员工呃再往上面加，也可以在右上角有一个选择员工，然后有一个加号键，你就把员工的信息给啊员工的信息、姓名、啊、证件号这些你给输入上去。然后入职时间呢，我们就填过营业执照以后的时间就可以了。印发工资呢，建议五千以下嗯，这个员工如果说没有在这你这家公司缴纳社保的话，这个缴纳社保的按钮你就不用管了。那如果说他有缴纳社保的话，你就把这个按钮给打开。",
        "emotion": "中立",
        "sales_strategy": "产品介绍",
        "customer_intent": "N/A-销售turn",
        "paralinguistic": [
          "无"
        ],
        "notes": "客户中间有多次嗯回应，未分离"
      }
    },
    {
      "turn_id": 15,
      "speaker": "customer",
      "start": 210.84,
      "end": 221.38,
      "duration_sec": 10.54,
      "input": {
        "text_asr": "我给你我帮您查一下，缴纳信时工，我发工资的时间选什么注册时间啊，不是应发工资那里，还是入职时间那里啊？",
        "wav_path": "data/S0000001/B0000004.wav",
        "auto_emotion_hint": "惊讶"
      },
      "output": {
        "transcript_corrected": "我给你我帮您查一下，缴纳信时工。我发工资的时间选什么注册时间啊？不是应发工资那里，还是入职时间那里啊？",
        "emotion": "惊讶",
        "sales_strategy": "N/A-客户turn",
        "customer_intent": "提问/深入了解",
        "paralinguistic": [
          "无"
        ],
        "notes": "开始是一段语音交叉，用户试图提问。销售再回答。我发工资的时间选什么注册时间啊？这句是用户的，剩下都是销售的。未分割"
      }
    },
    {
      "turn_id": 16,
      "speaker": "sales",
      "start": 221.38,
      "end": 229.95,
      "duration_sec": 8.57,
      "input": {
        "text_asr": "呃，应发工资那个入职时间那块抓起来，嗯，过营业执照以后的时间都可以的。",
        "wav_path": "data/S0000001/A0000011.wav",
        "auto_emotion_hint": "中立"
      },
      "output": {
        "transcript_corrected": "呃，应发工资那个入职时间那块咋选呢？嗯，过营业执照以后的时间都可以的。",
        "emotion": "中立",
        "sales_strategy": "N/A-客户turn",
        "customer_intent": "提问/深入了解",
        "paralinguistic": [
          "无"
        ],
        "notes": "未分割对话，呃，应发工资那个入职时间那块咋选呢？是客户问的，后面销售回的"
      }
    },
    {
      "turn_id": 17,
      "speaker": "sales",
      "start": 229.95,
      "end": 388.31,
      "duration_sec": 158.36,
      "input": {
        "text_asr": "因为这个一五年注册的，我看你是五月二零一五年五月十五号。那你你现在填的话，你可以填，二零二五年一月一日都可以。嗯，嘿，只要是过营业执照以后的时间都可以的。你还要后面社保不写不缴纳嗯，没有缴纳的话就不用管，然后保存就可以了。嗯，啊这里就是添加员工的一个页面，就是有其他员工的话，还是按照这个步骤来添加的。嗯嗯，嗯后期如果说没有变动就不用管了。那第二步呢，就是获取发票。首先第一个是自动采集区，就是咱公司有开的销像票和进项票，这边它能都能是每个月一到五号自动采集。比如说十一月份的话，我们要申报十月份的了。那你十月一号到十月三十一号开的所有的肖项票和进项票。我们这个小程序它是直连税务局的都能都是能自动抓取的。这个你也不用管你，只要是登录电子税务局去开，我们这边都是能自动采集的。嗯嗯，啊然后下面有一个手动上传区，就是比如说有一些费用小票，像出差的呀，呃这个差旅费呀、住宿费啊这些呃不在咱公司采购的一些纸质票据，你可以多张小票放在一起拍照录入。作为公司的成本，我们做账的话也会给您做到账里面。嗯，这个发票的话是就就是只有这些。第三步的话就是上传流水，就是咱对公账户的往来呃，流水。比如说就是说嗯你打给对方的钱，或者是对方打给你的钱，咱们的这个流水。嗯，咱们每个月月初的时候，把这个流水导出来，导出excel的格式上传到这个小程序上就可以了。嗯，可以手机上传，也可以电脑上传。嗯，就是说导出流水的话，你对公账户银行是哪个银行，我们会给您指导，怎么导出来？嗯，怎么导出流水？我们会给您做指导一两分钟的时间就弄好了，这个也挺简单的。嗯，整个的需要操作的，你唯一需要操作的，就是说咱们公司也创建了，你员工也添加了。那你每个月需要操作的，就是说上传流水就可以了。这边我们合作以后呢，我们会呃一家公司给你建一个群群，里面是匹配一个人工会计老师，两个会计助理。他们三个呢就是给咱全程跟踪服务的。首先呢我们就是建群以后给您验一下税密，就是咱电子税务局的登录密码。嗯，我们的会计呢会添加为咱公司的办税员，每个月到申报期了。",
        "wav_path": "data/S0000001/A0000012.wav",
        "auto_emotion_hint": "中立"
      },
      "output": {
        "transcript_corrected": "因为这个一五年注册的，我看你是五月二零一五年五月十五号。那你你现在填的话，你可以填，二零二五年一月一日都可以。只要是过营业执照以后的时间都可以的。你还要后面社保不写不缴纳。嗯，没有缴纳的话就不用管，然后保存就可以了。嗯。啊这里就是添加员工的一个页面，就是有其他员工的话，还是按照这个步骤来添加的。嗯嗯。嗯后期如果说没有变动就不用管了。那第二步呢，就是获取发票。首先第一个是自动采集区，就是咱公司有开的收项票和进项票，这边它能都能是每个月一到五号自动采集。比如说十一月份的话，我们要申报十月份的了。那你十月一号到十月三十一号开的所有的收项票和进项票。我们这个小程序它是直连税务局的都能都是能自动抓取的。这个你也不用管你，只要是登录电子税务局去开，我们这边都是能自动采集的。嗯嗯，啊然后下面有一个手动上传区，就是比如说有一些费用小票，像出差的呀，呃这个差旅费呀、住宿费啊这些呃不在咱公司采购的一些纸质票据，你可以多张小票放在一起拍照录入。作为公司的成本，我们做账的话也会给您做到账里面。嗯，这个发票的话是就就是只有这些。第三步的话就是上传流水，就是咱对公账户的往来呃，流水。比如说就是说嗯你打给对方的钱，或者是对方打给你的钱，咱们的这个流水。嗯，咱们每个月月初的时候，把这个流水导出来，导出excel的格式上传到这个小程序上就可以了。嗯，可以手机上传，也可以电脑上传。嗯，就是说导出流水的话，你对公账户银行是哪个银行，我们会给您指导，怎么导出来？嗯，怎么导出流水？我们会给您做指导一两分钟的时间就弄好了，这个也挺简单的。嗯，整个的需要操作的，你唯一需要操作的，就是说咱们公司也创建了，你员工也添加了。那你每个月需要操作的，就是说上传流水就可以了。这边我们合作以后呢，我们会呃一家公司给你建一个群群，里面是匹配一个人工会计老师，两个会计助理。他们三个呢就是给咱全程跟踪服务的。首先呢我们就是建群以后给您验一下税密，就是咱电子税务局的登录密码。嗯，我们的会计呢会添加为咱公司的办税员，每个月到申报期了。",
        "emotion": "中立",
        "sales_strategy": "产品介绍",
        "customer_intent": "N/A-销售turn",
        "paralinguistic": [
          "无"
        ],
        "notes": null
      }
    },
    {
      "turn_id": 18,
      "speaker": "customer",
      "start": 388.31,
      "end": 423.85,
      "duration_sec": 35.54,
      "input": {
        "text_asr": "然后你点开那个最下面有一个报税的页面，你看一下一个，我看我有十个税务，然后呃有些他们出去的出有那个出差补贴，有那个过渡费，还有这些费用费用小票是吧？那个不是小票，就就是那个小票学一部分，还有那个就是什么学一部分，那个哎那个银块，比如说住酒店啊什么的，这些的过渡啊，票呀这些的那些这个东西会自动采集。那采集完以后，比如我这十个人怎么去给他们分配是谁的费用啊，什么这些啊。",
        "wav_path": "data/S0000001/B0000005.wav",
        "auto_emotion_hint": "中立"
      },
      "output": {
        "transcript_corrected": "然后你点开那个最下面有一个报税的页面，你看一下一个，我看我有十个人吧。然后呃有些他们出去的出有那个出差补贴，有那个过路费，还有这些费用费用小票是吧？那个不是小票，就就是那个小票是一部分，还有那个就是什么学一部分，那个哎那个，比如说住酒店啊什么的，这些的过路啊，票呀这些的那些这个东西会自动采集。那采集完以后，比如我这十个人怎么去给他们分配是谁的费用啊，什么这些啊。",
        "emotion": "中立",
        "sales_strategy": "N/A-客户turn",
        "customer_intent": "提问/深入了解",
        "paralinguistic": [
          "无"
        ],
        "notes": "里面还是存在未分割对话，不过主要是用户在提问。"
      }
    },
    {
      "turn_id": 19,
      "speaker": "sales",
      "start": 423.85,
      "end": 445.73,
      "duration_sec": 21.88,
      "input": {
        "text_asr": "这个的话，你们不是有内内部的会计吗？你你他那个费用的话，我们分配费用只是按那个我们会计入账，他只是按就是说报销了呀。这些就是每个人每个人的是呃，就是说你们你们不是有会计嘛，然后你们就是给他给他就是啊你们是记个专专门的，就记这个大类是吧？",
        "wav_path": "data/S0000001/A0000013.wav",
        "auto_emotion_hint": "中立"
      },
      "output": {
        "transcript_corrected": "这个的话，你们不是有内内部的会计吗？你你他那个费用的话，我们分配费用只是按那个我们会计入账，他只是按就是说报销了呀。这些就是每个人每个人的是呃，就是说你们你们不是有会计嘛，然后你们就是给他给他就是啊你们是记个专专门的，就记这个大类是吧？",
        "emotion": "中立",
        "sales_strategy": "异议处理",
        "customer_intent": "N/A-销售turn",
        "paralinguistic": [
          "无"
        ],
        "notes": "客户在最后回复了。未分割"
      }
    },
    {
      "turn_id": 20,
      "speaker": "sales",
      "start": 445.73,
      "end": 450.31,
      "duration_sec": 4.58,
      "input": {
        "text_asr": "我不管对对对，我们就是啊啊啊就是报外账的。",
        "wav_path": "data/S0000001/A0000014.wav",
        "auto_emotion_hint": "中立"
      },
      "output": {
        "transcript_corrected": "我们就是啊啊啊就是报外账的。",
        "emotion": "中立",
        "sales_strategy": "产品介绍",
        "customer_intent": "N/A-销售turn",
        "paralinguistic": [
          "无"
        ],
        "notes": null
      }
    },
    {
      "turn_id": 21,
      "speaker": "customer",
      "start": 450.31,
      "end": 461.29,
      "duration_sec": 10.98,
      "input": {
        "text_asr": "嗯，那你这个报销那个什么呃，还有就是那个比如说我这个发票里面有好多种西加油的过路的什么这种的那这个东西来说，比如说你也是会建分类是吧？",
        "wav_path": "data/S0000001/B0000006.wav",
        "auto_emotion_hint": "中立"
      },
      "output": {
        "transcript_corrected": "嗯，那你这个报销那个什么呃，还有就是那个比如说我这个发票里面有好多种有加油的过路的什么这种的那这个东西来说，比如说你也是会建分类是吧？",
        "emotion": "中立",
        "sales_strategy": "N/A-客户turn",
        "customer_intent": "提问/深入了解",
        "paralinguistic": [
          "无"
        ],
        "notes": null
      }
    },
    {
      "turn_id": 22,
      "speaker": "sales",
      "start": 461.29,
      "end": 683.45,
      "duration_sec": 222.16,
      "input": {
        "text_asr": "啊，对对对，我们快递会给你做分类啊，就是我们采集好以后，采集了以后会做分类啊，那你你们手动来给你做分类是吧？嗯，我们的会计呢，你点开那个报废的页面，最下面我们的会递他是嗯就是说我们不是说给你个小程程序，然后采集发票，我们这边就没有人工管了。我们是AI加人工，咱们不是群里面是给您匹配的，有人工会计老师嘛，三个会计老师，他们有做账的，邮件私密的有主会计，老师有会计助理。嗯，他们就是会计，他会添加给你公司的办税员。那到申报期了，他会就检查咱提交的一个记账资料发票呀，流水去给咱进行呃核对。核对好以后，他会给他问题了。就是说他检查的问题，他会在群里面跟您说，咱们进行核对，核对无误以后，再提交税务局去呃，申报。不是说我们就是说呃采集的资料，我们连看都不看，直接给您申报了。不是这样的，他会给您做审核，审核好以后再申报，并且申报的结果。那在第五步啊，第五步，我们本院去申报申报的结果有没有申报报税的一个截图。呃，都是在这里面可以看得到的，就是我们本月给您申报哪些税种呀，产生了多少多少的税费，你都是可以在第五处查看的。这个你明白吗？就是这个报税的一个流程。然后还有一个就是报税的下面报税的右边有一个发票，你看到没对。嗯，这个上面呢就是它能采集到你呃，就是说咱们合作以后，他能采集到你往来的发票。就是咱今年的发票呃，销项票多少张多少金额，进项票多少张多少金额，它是能采集的到的。所以说呃你可以清楚的知道本年咱们公司开了多少销项票，多少进项票。就是说如果说进项票少的话，咱们及时归集咱的一个呃成本嘛，是吧？嗯嗯，这样的话可以，你在呃在上面可以看得到，就是也不用你进入电子税务局，这上面都是能清楚的。它是跟税务局直连的，就是呃，发票的情况就反映在这上面了。那税后呃右下角有一个我的你点开看一下。嗯，啊然后这边有一个发票，银行税务和报表。那我们的发票情况这里也可以看得到，银行的流水也可以看得到。我们税务申报的情况也可以在这里看得到。那这个绿色的部分就是这个报表的部分，我们给您做的财务报表。你可以点开上面有一个资产负债表呀，利润表这些呃你都是可以查看每个月份的可以选择，可以预览下载打印都是可以的这是我们给您做的财务报表。你可以实时掌控吗？随时随地都可以开整个我们小程序操作的整个的一个报税流程。就这些。然后下面有一个新增公司，就比如说你有其他的公司，嗯，然后需要跟我们合作的话，这里有一个新增公司，你点开的话，还可以把其他的公司就是放进来。然后咱们是一家公司开通一个会员，但是一个小程序上它可以挂靠很多家公司。嗯，还有一个就是公司授权嘛，就是说这个你不想操作的话，像你公司里有文员，或者你有时间操作操作。这个因为现在你公司已经创建好了，你只需要就是说让你的公司的文员呀，或者是你你刚才说的，你公司有快递，你让他你把这个公司有一个公司授权，你把小程序发给他，让他注册登录以后，就是跟刚才一样接受个验证码注册登录。然后这有一个添加授权，你把公司授权到他的手机号上，这样的话他也可以操作，你也可以查看你们两个同时都是可以用的对不？",
        "wav_path": "data/S0000001/A0000015.wav",
        "auto_emotion_hint": "中立"
      },
      "output": {
        "transcript_corrected": "啊，对对对，我们会计会给你做分类啊，就是我们采集好以后，采集了以后会做分类啊，那你你们手动来给你做分类是吧？嗯，我们的会计呢，你点开那个报税的页面，最下面我们的会计他是嗯就是说我们不是说给你个小程程序，然后采集发票，我们这边就没有人工管了。我们是AI加人工，咱们不是群里面是给您匹配的，有人工会计老师嘛，三个会计老师，他们有做账的，有验税密的，有主会计老师，有会计助理。嗯，他们就是会计，他会添加给你公司的办税员。那到申报期了，他会就检查咱提交的一个记账资料发票呀，流水去给咱进行呃核对。核对好以后，然后没有问题了。就是说他检查的问题，他会在群里面跟您说，咱们进行核对，核对无误以后，再提交税务局去呃，申报。不是说我们就是说呃采集的资料，我们连看都不看，直接给您申报了。不是这样的，他会给您做审核，审核好以后再申报，并且申报的结果。那在第五步啊，第五步，我们本月去申报申报的结果有没有申报报税的一个截图。呃，都是在这里面可以看得到的，就是我们本月给您申报哪些税种呀，产生了多少多少的税费，你都是可以在第五步查看的。这个你明白吗？就是这个报税的一个流程。然后还有一个就是报税的下面报税的右边有一个发票，你看到没对。嗯，这个上面呢就是它能采集到你呃，就是说咱们合作以后，他能采集到你往来的发票。就是咱今年的发票呃，销项票多少张多少金额，进项票多少张多少金额，它是能采集的到的。所以说呃你可以清楚的知道本年咱们公司开了多少销项票，多少进项票。就是说如果说进项票少的话，咱们及时归集咱的一个呃成本嘛，是吧？嗯嗯，这样的话可以，你在呃在上面可以看得到，就是也不用你进入电子税务局，这上面都是能清楚的。它是跟税务局直连的，就是呃，发票的情况就反映在这上面了。那税后呃右下角有一个我的你点开看一下。嗯，啊然后这边有一个发票，银行税务和报表。那我们的发票情况这里也可以看得到，银行的流水也可以看得到。我们税务申报的情况也可以在这里看得到。那这个绿色的部分就是这个报表的部分，我们给您做的财务报表。你可以点开上面有一个资产负债表呀，利润表这些呃你都是可以查看每个月份的可以选择，可以预览下载打印都是可以的这是我们给您做的财务报表。你可以实时掌控吗？随时随地都可以开整个我们小程序操作的整个的一个报税流程。就这些。然后下面有一个新增公司，就比如说你有其他的公司，嗯，然后需要跟我们合作的话，这里有一个新增公司，你点开的话，还可以把其他的公司就是放进来。然后咱们是一家公司开通一个会员，但是一个小程序上它可以挂靠很多家公司。嗯，还有一个就是公司授权嘛，就是说这个你不想操作的话，像你公司里有文员，或者你没有时间操作操作。这个因为现在你公司已经创建好了，你只需要就是说让你的公司的文员呀，或者是你你刚才说的，你公司有快递，你让他你把这个公司有一个公司授权，你把小程序发给他，让他注册登录以后，就是跟刚才一样接受个验证码注册登录。然后这有一个添加授权，你把公司授权到他的手机号上，这样的话他也可以操作，你也可以查看你们两个同时都是可以用的。",
        "emotion": "中立",
        "sales_strategy": "产品介绍",
        "customer_intent": "N/A-销售turn",
        "paralinguistic": [
          "无"
        ],
        "notes": null
      }
    },
    {
      "turn_id": 23,
      "speaker": "sales",
      "start": 683.45,
      "end": 696.69,
      "duration_sec": 13.24,
      "input": {
        "text_asr": "嗯，咱咱咱那个贷账是什么时候到期啊，到期也没有说到期不到期了，反正就这么一直用的哦，就是自己能弄的是吧？",
        "wav_path": "data/S0000001/A0000016.wav",
        "auto_emotion_hint": "中立"
      },
      "output": {
        "transcript_corrected": "嗯，咱咱咱那个贷账是什么时候到期啊，到期也没有说到期不到期了，反正就这么一直用的哦，就是自己能弄的是吧？",
        "emotion": "中立",
        "sales_strategy": "逼单/促成",
        "customer_intent": "N/A-销售turn",
        "paralinguistic": [
          "无"
        ],
        "notes": "未分割，有对话"
      }
    },
    {
      "turn_id": 24,
      "speaker": "sales",
      "start": 696.69,
      "end": 768.265,
      "duration_sec": 71.575,
      "input": {
        "text_asr": "嗯，啊自己人弄的话，你就是说你感觉就是说咱们可以的话，下个月也可以记录。呃，也开始。就是因为咱们一般纳税人是每个月都要申报的，刚好这也是月底了，下个月我们也要开始申报十月份的了。所以说你可以就是考虑。嗯，对，接到我们这边，咱们虽然是按年收费的，但是是按月扣费的，体验一下我们的服务和报税的流程。哎，感觉满意的话，到时候咱们再就是说嗯呃咱们就是一直合作。如果说感觉呃不满意的话，也没有关系。咱们那我们给您报一个月就扣一个月的费用，剩余的盖章费用我们也会原路返还给你的。并且呢就是说咱们是这个月已经申报完了，下月申报的话，你就是咱今天签合同的话，我会把盖章日期给你改到下个月开始。前期的话，咱们先在群里面配合会计老师把那个顺利验一下。前期的费用交接好以后，对接好以后，那到十一月一号开始，我们就直接给您申报的嗯优先申报。那你也可以就是尽早的在上面查看一下申报的结果，和我们的一个提前体验一下我们的一个服务。",
        "wav_path": "data/S0000001/A0000017.wav",
        "auto_emotion_hint": "中立"
      },
      "output": {
        "transcript_corrected": "嗯，啊自己人弄的话，你就是说你感觉就是说咱们可以的话，下个月也可以记录。呃，也开始。就是因为咱们一般纳税人是每个月都要申报的，刚好这也是月底了，下个月我们也要开始申报十月份的了。所以说你可以就是考虑。嗯，对接到我们这边，咱们虽然是按年收费的，但是是按月扣费的，体验一下我们的服务和报税的流程。哎，感觉满意的话，到时候咱们再就是说嗯呃咱们就是一直合作。如果说感觉呃不满意的话，也没有关系。咱们那我们给您报一个月就扣一个月的费用，剩余的代账费用我们也会原路返还给你的。并且呢就是说咱们是这个月已经申报完了，下月申报的话，你就是咱今天签合同的话，我会把盖章日期给你改到下个月开始。前期的话，咱们先在群里面配合会计老师把那个顺利验一下。前期的费用交接好以后，对接好以后，那到十一月一号开始，我们就直接给您申报的嗯优先申报。那你也可以就是尽早的在上面查看一下申报的结果，和我们的一个提前体验一下我们的一个服务。",
        "emotion": "中立",
        "sales_strategy": "逼单/促成",
        "customer_intent": "N/A-销售turn",
        "paralinguistic": [
          "无"
        ],
        "notes": null
      }
    },
    {
      "turn_id": 25,
      "speaker": "customer",
      "start": 769.14,
      "end": 773.84,
      "duration_sec": 4.7,
      "input": {
        "text_asr": "不敢说啊，这个嗯目前我还没有打算改模式改正，直接改。",
        "wav_path": "data/S0000001/B0000007.wav",
        "auto_emotion_hint": "中立"
      },
      "output": {
        "transcript_corrected": "不敢说啊，这个嗯目前我还没有打算改模式改正，直接改。",
        "emotion": "中立",
        "sales_strategy": "N/A-客户turn",
        "customer_intent": "软拒绝（找借口）",
        "paralinguistic": [
          "无"
        ],
        "notes": null
      }
    },
    {
      "turn_id": 26,
      "speaker": "customer",
      "start": 773.84,
      "end": 778.63,
      "duration_sec": 4.79,
      "input": {
        "text_asr": "我们账太乱，那账太多的也不太乱了，就没人改。",
        "wav_path": "data/S0000001/B0000008.wav",
        "auto_emotion_hint": "中立"
      },
      "output": {
        "transcript_corrected": "我们账太乱，那账太多的也不太乱了，就没人改。",
        "emotion": "中立",
        "sales_strategy": "N/A-客户turn",
        "customer_intent": "软拒绝（找借口）",
        "paralinguistic": [
          "无"
        ],
        "notes": null
      }
    },
    {
      "turn_id": 27,
      "speaker": "customer",
      "start": 778.63,
      "end": 783.47,
      "duration_sec": 4.84,
      "input": {
        "text_asr": "嗯，您您说的是有交给代账公司做是吧？",
        "wav_path": "data/S0000001/B0000009.wav",
        "auto_emotion_hint": "中立"
      },
      "output": {
        "transcript_corrected": "嗯，您您上次说的是有交给代账公司做是吧？",
        "emotion": "中立",
        "sales_strategy": "逼单/促成",
        "customer_intent": "N/A-销售turn",
        "paralinguistic": [
          "无"
        ],
        "notes": null
      }
    },
    {
      "turn_id": 28,
      "speaker": "customer",
      "start": 783.67,
      "end": 792.3,
      "duration_sec": 8.63,
      "input": {
        "text_asr": "嗯，用那个我的专专一弄我的，好多人理的顺吧，咖理顺啊，他有给你做账吗？",
        "wav_path": "data/S0000001/B0000010.wav",
        "auto_emotion_hint": "中立"
      },
      "output": {
        "transcript_corrected": "嗯，用那个我的专门弄我的，我这好不容易理得顺吧，刚理顺啊，他有给你做账吗？",
        "emotion": "中立",
        "sales_strategy": "N/A-客户turn",
        "customer_intent": "软拒绝（找借口）",
        "paralinguistic": [
          "无"
        ],
        "notes": "有对话，未分割。销售问他有给你做账吗？"
      }
    },
    {
      "turn_id": 29,
      "speaker": "sales",
      "start": 792.3,
      "end": 800.66,
      "duration_sec": 8.36,
      "input": {
        "text_asr": "嗯嗯，有了做到外上是吧？你坐到外上的话，你到时候嗯你如果说对接我们这边也挺简单的，你就是让他给你导出。",
        "wav_path": "data/S0000001/A0000018.wav",
        "auto_emotion_hint": "中立"
      },
      "output": {
        "transcript_corrected": "嗯嗯，有了做到外账是吧？你做的外账的话，你到时候嗯你如果说对接我们这边也挺简单的，你就是让他给你导出。",
        "emotion": "中立",
        "sales_strategy": "逼单/促成",
        "customer_intent": "N/A-销售turn",
        "paralinguistic": [
          "无"
        ],
        "notes": null
      }
    },
    {
      "turn_id": 30,
      "speaker": "sales",
      "start": 800.66,
      "end": 808.95,
      "duration_sec": 8.29,
      "input": {
        "text_asr": "嗯，我们会快递，他会发一些对账交接的资料需要哪些，然后你让他给你导出就行了，要到时候再说。",
        "wav_path": "data/S0000001/A0000019.wav",
        "auto_emotion_hint": "中立"
      },
      "output": {
        "transcript_corrected": "嗯，我们呢会计，他会发一些对账交接的资料需要哪些，然后你让他给你导出就行了。要到时候再说吧。",
        "emotion": "中立",
        "sales_strategy": null,
        "customer_intent": "软拒绝（找借口）",
        "paralinguistic": [
          "无"
        ],
        "notes": "有对话，客户回答：要到时候再说吧。未分割"
      }
    },
    {
      "turn_id": 31,
      "speaker": "customer",
      "start": 808.95,
      "end": 816.86,
      "duration_sec": 7.91,
      "input": {
        "text_asr": "我我的从一五年到现在账挺多的，能弄的还是挺多的啊。",
        "wav_path": "data/S0000001/B0000011.wav",
        "auto_emotion_hint": "中立"
      },
      "output": {
        "transcript_corrected": "我我的从一五年到现在账挺多的，能弄的还是挺多的啊。",
        "emotion": "中立",
        "sales_strategy": "N/A-客户turn",
        "customer_intent": "软拒绝（找借口）",
        "paralinguistic": [
          "无"
        ],
        "notes": null
      }
    },
    {
      "turn_id": 32,
      "speaker": "customer",
      "start": 816.86,
      "end": 825.38,
      "duration_sec": 8.52,
      "input": {
        "text_asr": "嗯嗯，流水，我说你这这这几年一年流水一千来万，各种票也挺多，乱七八糟的这些嗯那也挺不错的呀。",
        "wav_path": "data/S0000001/B0000012.wav",
        "auto_emotion_hint": "中立"
      },
      "output": {
        "transcript_corrected": "嗯嗯，流水，我说你这这这几年一年流水一千来万，各种票也挺多，乱七八糟的这些嗯那也挺不错的呀。",
        "emotion": "中立",
        "sales_strategy": "N/A-客户turn",
        "customer_intent": "软拒绝（找借口）",
        "paralinguistic": [
          "无"
        ],
        "notes": null
      }
    },
    {
      "turn_id": 33,
      "speaker": "sales",
      "start": 825.38,
      "end": 898.83,
      "duration_sec": 73.45,
      "input": {
        "text_asr": "啊，现在都是竖店票了，就是说所有的发票这些呃这一类的就是全部登录电子税务局就直接可以开了。并且别人开给你的啊，给别人开给你的也可以。就是说嗯在电子税务局里可以涉及到我们小程序能采集得到。嗯，行吧？嗯，行，那反正小程序你也了解了，对吧？反正到时候你考虑嘛。如果说嗯想在我们这里盖账的话，填一下我们的父母，看我们的一个报备，跟你找的代账公司呃，基本呃基本上都是一样的。他也是登陆电子税务局，每个月去给您申报。你找的那个会递他，你们公司请的会计是给您做内账的是吧？嗯，那也没有关系啊，你可以把到时候我们建群的话，你可以把会计也拉到群里边，有什么问题。他可以在我呃在群里面跟我们的会计老师沟通，就是我们合作以后也会把会计老师的电话发到群里面嘛，发到群里面。然后有什么问题你们都可以随时给他打电话，然后来给他进行沟通的。嗯，虽然咱们是在啊，虽然咱们现场申报，但是咱们也是由人工快递来服务的。",
        "wav_path": "data/S0000001/A0000020.wav",
        "auto_emotion_hint": "中立"
      },
      "output": {
        "transcript_corrected": "啊，现在都是数电票了，就是说所有的发票这些呃这一类的就是全部登录电子税务局就直接可以开了。并且别人开给你的啊，给别人开给你的也可以。就是说嗯在电子税务局里可以涉及到我们小程序能采集得到。嗯，行吧？嗯，行，那反正小程序你也了解了，对吧？反正到时候你考虑嘛。如果说嗯想在我们这里代账的话，体验一下我们的服务，看我们的一个报税，跟你找的代账公司呃，基本呃基本上都是一样的。他也是登陆电子税务局，每个月去给您申报。你找的那个会计他，你们公司请的会计是给您做内账的是吧？嗯，那也没有关系啊，你可以把到时候我们建群的话，你可以把会计也拉到群里边，有什么问题。他可以在我呃在群里面跟我们的会计老师沟通，就是我们合作以后也会把会计老师的电话发到群里面嘛，发到群里面。然后有什么问题你们都可以随时给他打电话，然后来给他进行沟通的。嗯，虽然咱们是在啊，虽然咱们现场申报，但是咱们也是由人工会计来服务的。",
        "emotion": "中立",
        "sales_strategy": "逼单/促成",
        "customer_intent": "N/A-销售turn",
        "paralinguistic": [
          "无"
        ],
        "notes": null
      }
    },
    {
      "turn_id": 34,
      "speaker": "customer",
      "start": 898.83,
      "end": 903.65,
      "duration_sec": 4.82,
      "input": {
        "text_asr": "人工嗯嗯，行，你你这边就是我，我需要等啊，咱们再联系好吧。",
        "wav_path": "data/S0000001/B0000013.wav",
        "auto_emotion_hint": "中立"
      },
      "output": {
        "transcript_corrected": "人工嗯嗯，行，你你这边就是我，我需要等啊，等晚一些咱们再联系好吧。",
        "emotion": "中立",
        "sales_strategy": "N/A-客户turn",
        "customer_intent": "软拒绝（找借口）",
        "paralinguistic": [
          "无"
        ],
        "notes": null
      }
    },
    {
      "turn_id": 35,
      "speaker": "sales",
      "start": 903.71,
      "end": 915.385,
      "duration_sec": 11.675,
      "input": {
        "text_asr": "嗯，也行，反正咱俩有微信，你你就是备注一下，到时候有需要的话，反正小程序你也了解了。嗯，到时候你需要的话，你随时就是说给我发微信就可以了，好吧嗯嗯。",
        "wav_path": "data/S0000001/A0000021.wav",
        "auto_emotion_hint": "中立"
      },
      "output": {
        "transcript_corrected": "嗯，也行，反正咱俩有微信，你你就是备注一下，到时候有需要的话，反正小程序你也了解了。嗯，到时候你需要的话，你随时就是说给我发微信就可以了，好吧嗯嗯。",
        "emotion": "中立",
        "sales_strategy": "关系维护/寒暄",
        "customer_intent": "N/A-销售turn",
        "paralinguistic": [
          "无"
        ],
        "notes": null
      }
    }
  ]
}